EdgeClassifier/__init__.py
EdgeClassifier/activator.py
EdgeClassifier/edge_classifier.py
EdgeClassifier/features_builder.py
EdgeClassifier/model.py
EdgeClassifier/mydataset.py
EdgeClassifier/params_model.py
EdgeClassifier-0.0.11.dist-info/METADATA
EdgeClassifier-0.0.11.dist-info/WHEEL
EdgeClassifier-0.0.11.dist-info/top_level.txt
EdgeClassifier-0.0.11.dist-info/RECORD
