Metadata-Version: 2.1
Name: EdgeClassifier
Version: 0.0.11
Summary: A python package for classify edges of graph based on topological features and neural networks.
Home-page: https://github.com/louzounlab/Edge-Prediction
Author: Ziv Naim
Maintainer: Ziv Naim
Maintainer-email: zivnaim3@gmail.com
License: MIT
Keywords: gpu,graph,edges,edge,classification,neural,networks
Classifier: Programming Language :: Python
Requires-Python: >=3.6.8
Requires-Dist: networkx
Requires-Dist: torch
Requires-Dist: matplotlib
Requires-Dist: numpy
Requires-Dist: scikit-learn
Requires-Dist: tqdm
Requires-Dist: graph-measures (==0.1.51)
